COPYING
MANIFEST.in
README.rst
setup.cfg
setup.py
versioneer.py
connections/socnews.sh
connections/socsmtp.sh
connections/stunnel-whonix.conf
connections/stunnel.conf
docs/Makefile
docs/make.bat
docs/.ropeproject/config.py
docs/.ropeproject/globalnames
docs/.ropeproject/history
docs/.ropeproject/objectdb
docs/build/doctrees/changelog.doctree
docs/build/doctrees/environment.pickle
docs/build/doctrees/feedback.doctree
docs/build/doctrees/index.doctree
docs/build/doctrees/overview.doctree
docs/build/doctrees/thanks.doctree
docs/build/doctrees/install/connections-whonix.doctree
docs/build/doctrees/install/connections.doctree
docs/build/doctrees/install/dependencies.doctree
docs/build/doctrees/install/mixmaster-whonix.doctree
docs/build/doctrees/install/mixmaster.doctree
docs/build/doctrees/install/newsserver.doctree
docs/build/doctrees/use/composition.doctree
docs/build/doctrees/use/configuration.doctree
docs/build/doctrees/use/counter.doctree
docs/build/doctrees/use/creation.doctree
docs/build/doctrees/use/decryption.doctree
docs/build/doctrees/use/files.doctree
docs/build/doctrees/use/keyring.doctree
docs/build/doctrees/use/login.doctree
docs/build/html/.buildinfo
docs/build/html/changelog.html
docs/build/html/feedback.html
docs/build/html/genindex.html
docs/build/html/index.html
docs/build/html/objects.inv
docs/build/html/overview.html
docs/build/html/search.html
docs/build/html/searchindex.js
docs/build/html/thanks.html
docs/build/html/_images/agent.png
docs/build/html/_images/configured.png
docs/build/html/_images/counter.png
docs/build/html/_images/create.png
docs/build/html/_images/created.png
docs/build/html/_images/e2e.png
docs/build/html/_images/inbox-body.png
docs/build/html/_images/inbox-headers.png
docs/build/html/_images/key.png
docs/build/html/_images/login.png
docs/build/html/_images/nym_not_found.png
docs/build/html/_images/send.png
docs/build/html/_images/sent.png
docs/build/html/_images/servers.png
docs/build/html/_sources/changelog.txt
nymphemeral.egg-info/PKG-INFO
nymphemeral.egg-info/SOURCES.txt
nymphemeral.egg-info/dependency_links.txt
nymphemeral.egg-info/entry_points.txt
nymphemeral.egg-info/requires.txt
nymphemeral.egg-info/top_level.txt
