Metadata-Version: 1.1
Name: nymphemeral
Version: 1.4.2.1
Summary: An ephemeral nym GUI client
Home-page: https://github.com/felipedau/nymphemeral
Author: Felipe Dau
Author-email: dau.felipe@gmail.com
License: GPL
Keywords: nymphemeral ephemeral nymserver GUI client
Platform: UNKNOWN
Classifier: Development Status :: 4 - Beta
Classifier: Intended Audience :: Developers
Classifier: Intended Audience :: End Users/Desktop
Classifier: License :: OSI Approved :: GNU General Public License (GPL)
Classifier: Operating System :: POSIX :: Linux
Classifier: Programming Language :: Python :: 2.7
Classifier: Topic :: Communications :: Email
